pentest_header_analyzer/__init__.py
pentest_header_analyzer/header_analyzer.py
pentest_header_analyzer/utils.py
pentest_header_analyzer-0.1.1.dist-info/licenses/LICENSE
pentest_header_analyzer-0.1.1.dist-info/METADATA
pentest_header_analyzer-0.1.1.dist-info/WHEEL
pentest_header_analyzer-0.1.1.dist-info/entry_points.txt
pentest_header_analyzer-0.1.1.dist-info/top_level.txt
pentest_header_analyzer-0.1.1.dist-info/RECORD
