Metadata-Version: 2.4
Name: pentest-header-analyzer
Version: 0.1.1
Summary: A CLI tool for analyzing HTTP response headers for security misconfigurations.
Author: Root-huntress
License: MIT
Requires-Python: >=3.8
License-File: LICENSE
Requires-Dist: requests>=2.28.0
Requires-Dist: rich>=13.0.0
Dynamic: license-file
